chess_python/__init__.py
chess_python/chess.py
chess_python/game.py
chess_python/utils.py
chess_under_1000_lines-0.1.0.dist-info/WHEEL
chess_under_1000_lines-0.1.0.dist-info/METADATA
chess_under_1000_lines-0.1.0.dist-info/RECORD
