Metadata-Version: 2.1
Name: chess-under-1000-lines
Version: 0.1.0
Summary: Python implementation of the game of chess.
Author: pacanada
Author-email: pereirapcanada@gmail.com
Requires-Python: >=3.8,<4.0
Classifier: Programming Language :: Python :: 3
Classifier: Programming Language :: Python :: 3.8
Classifier: Programming Language :: Python :: 3.9
Classifier: Programming Language :: Python :: 3.10
Requires-Dist: numpy (>=1.23.3,<2.0.0)
